geoma/__init__.py
geoma/shape.py
geoma-0.0.1.dist-info/METADATA
geoma-0.0.1.dist-info/WHEEL
geoma-0.0.1.dist-info/licenses/LICENSE
geoma-0.0.1.dist-info/RECORD
