Metadata-Version: 2.4
Name: geoma
Version: 0.0.1
Summary: This is a library that will include geometric functions.
Author: mikhail
License-File: LICENSE
Classifier: License :: OSI Approved :: MIT License
Classifier: Operating System :: OS Independent
Classifier: Programming Language :: Python :: 3
Requires-Python: >=3.10.0
